AnosysLoggers/__init__.py
AnosysLoggers/tracing.py
anosys_openai_agents_logger-0.0.20.dist-info/licenses/LICENSE
anosys_openai_agents_logger-0.0.20.dist-info/METADATA
anosys_openai_agents_logger-0.0.20.dist-info/WHEEL
anosys_openai_agents_logger-0.0.20.dist-info/top_level.txt
anosys_openai_agents_logger-0.0.20.dist-info/RECORD
